pydrew/__init__.py
pydrew/modules/__init__.py
pydrew/modules/dictionary.py
pydrew/modules/list.py
pydrew/tests/test_dictionary.py
pydrew/tests/test_list.py
pydrew-0.1.0.dist-info/METADATA
pydrew-0.1.0.dist-info/WHEEL
pydrew-0.1.0.dist-info/licenses/LICENSE
pydrew-0.1.0.dist-info/RECORD
