Metadata-Version: 2.3
Name: pydrew
Version: 0.1.0
Summary: A set of utilities for Python
Project-URL: Homepage, https://github.com/andreabbondanza/pydrew
Project-URL: Issues, https://github.com/andreabbondanza/pydrew/issues
Author-email: Andrea Vincenzo Abbondanza <andreabbondanza@gmail.com>
License-File: LICENSE
Classifier: License :: OSI Approved :: MIT License
Classifier: Operating System :: OS Independent
Classifier: Programming Language :: Python :: 3
Requires-Python: >=3.8
